[
   {
        "id":"0-0",
        "csub":[
            {
            	"src":"img/index/icon-surveillance.png",
                "x":"200",
                "y":"200"
            },
            {
            	"src":"img/index/icon-surveillance.png",
                "x":"200",
                "y":"300"
            }
        ]
    },
    {
        "id":"0-1",
        "csub":[
        	{
        		"src":"img/index/icon-surveillance.png",
                "x":"300",
                "y":"200"
        	},
        	{
        		"src":"img/index/icon-surveillance.png",
                "x":"300",
                "y":"400"
        	}
        ]
    },
    {
        "id":"0-2",
        "csub":[]
    },
    {
        "id":"0-3",
        "csub":[]
    },
    {
        "id":"0-4",
        "csub":[]
    },
    {
        "id":"0-5",
        "csub":[]
    },
    {
        "id":"0-6",
        "csub":[]
    },
    {
        "id":"0-7",
        "csub":[]
    },
    {
        "id":"0-8",
        "csub":[]
    },
    {
        "id":"0-10",
        "csub":[]
    }
]